pyso3/__init__.py
pyso3/check.py
pyso3/generate.py
pyso3/quaternion.py
pyso3/rodriguez.py
pyso3-0.0.1.dist-info/LICENSE.txt
pyso3-0.0.1.dist-info/METADATA
pyso3-0.0.1.dist-info/RECORD
pyso3-0.0.1.dist-info/WHEEL
pyso3-0.0.1.dist-info/top_level.txt
test/__init__.py
test/test_generate.py
test/test_quaternion.py
test/test_rodriguez.py
